{
    "items": {
        "1": {
            "rssTitle": "CFA I | trailer",
            "episode": 1,
            "title": "Trailer | 关于【CFA知识点】",
            "description": "<![CDATA[ <p> <b>【CFA知识点】</b>是一档记录一只金融小白，从零自学CFA的备考日记。 </p> </br> ]]>",
            "link": "https://s3.eu-central-1.wasabisys.com/audio.com.audio/transcoding/00/32/1786955878183200-1786955879954262-1786955887099729.mp3?X-Amz-Content-Sha256=UNSIGNED-PAYLOAD&X-Amz-Algorithm=AWS4-HMAC-SHA256&X-Amz-Credential=W7IA3NSYSOQIKLY9DEVC%2F20240617%2Feu-central-1%2Fs3%2Faws4_request&X-Amz-Date=20240617T172839Z&X-Amz-SignedHeaders=host&X-Amz-Expires=518400&X-Amz-Signature=4a0f0aa33e1d31eeb7b947db3d9a070d80be0049a172f91248b8af472e5508ad",
            "author": "羊小凡",
            "pubDate": "Fri, 19 Apr 2024 17:17:17 +0000",
            "length": "600045",
            "duration": "15"
        },
        "2": {
            "rssTitle": "EI_M1",
            "episode": 2,
            "title": "【Equity Investment】Market Organization and Structure",
            "description": "<![CDATA[ <p> <b>【Equity Investment】</b> Market Organization and Structure </p> </br> ]]>",
            "link": "https://s3.eu-central-1.wasabisys.com/audio.com.audio/transcoding/60/26/1788911370992660-1788911372844092-1788911452757611.mp3?X-Amz-Content-Sha256=UNSIGNED-PAYLOAD&X-Amz-Algorithm=AWS4-HMAC-SHA256&X-Amz-Credential=W7IA3NSYSOQIKLY9DEVC%2F20240617%2Feu-central-1%2Fs3%2Faws4_request&X-Amz-Date=20240617T172839Z&X-Amz-SignedHeaders=host&X-Amz-Expires=518400&X-Amz-Signature=6cb6ab9f0c0cbc42a0634a50aa86669bd9bf38c3d7c89e8d18e09175117a9e75",
            "author": "羊小凡",
            "pubDate": "Fri, 03 May 2024 17:17:17 +0000",
            "length": "15257749",
            "duration": "381"
        },
        "3": {
            "rssTitle": "EI_M3",
            "episode": 3,
            "title": "【Equity Investment】Market Efficiency",
            "description": "<![CDATA[ <p> <b>【Equity Investment】</b> Market Efficiency </p> </br> ]]>",
            "link": "https://s3.eu-central-1.wasabisys.com/audio.com.audio/transcoding/38/59/1789546451555938-1789546453603259-1789546460640066.mp3?X-Amz-Content-Sha256=UNSIGNED-PAYLOAD&X-Amz-Algorithm=AWS4-HMAC-SHA256&X-Amz-Credential=W7IA3NSYSOQIKLY9DEVC%2F20240617%2Feu-central-1%2Fs3%2Faws4_request&X-Amz-Date=20240617T172839Z&X-Amz-SignedHeaders=host&X-Amz-Expires=518400&X-Amz-Signature=1ec8339521373407c63b2db81562383726e27a0fae258f55fa5aa4c200d506fd",
            "author": "羊小凡",
            "pubDate": "Fri, 17 May 2024 17:17:17 +0000",
            "length": "6774222",
            "duration": "169"
        },
        "4": {
            "rssTitle": "EI_M2",
            "episode": 4,
            "title": "【Equity Investment】Security Market Indexes",
            "description": "<![CDATA[ <p> <b>【Equity Investment】</b> Security Market Indexes </p> </br> ]]>",
            "link": "https://s3.eu-central-1.wasabisys.com/audio.com.audio/transcoding/03/91/1789546136589103-1789546138400503-1789546164132977.mp3?X-Amz-Content-Sha256=UNSIGNED-PAYLOAD&X-Amz-Algorithm=AWS4-HMAC-SHA256&X-Amz-Credential=W7IA3NSYSOQIKLY9DEVC%2F20240617%2Feu-central-1%2Fs3%2Faws4_request&X-Amz-Date=20240617T172839Z&X-Amz-SignedHeaders=host&X-Amz-Expires=518400&X-Amz-Signature=eb0694a7e8ecb273bcbdb2fb7ddfe32290c03ccda70e65723a7143a58277826d",
            "author": "羊小凡",
            "pubDate": "Fri, 10 May 2024 17:17:17 +0000",
            "length": "9503496",
            "duration": "238"
        },
        "5": {
            "rssTitle": "EI_M4",
            "episode": 5,
            "title": "【Equity Investment】Overview of Equity Securities",
            "description": "<![CDATA[ <p> <b>【Equity Investment】</b> Overview of Equity Securities </p> </br> ]]>",
            "link": "https://s3.eu-central-1.wasabisys.com/audio.com.audio/transcoding/70/22/1789546864842270-1789546866685697-1789546888738963.mp3?X-Amz-Content-Sha256=UNSIGNED-PAYLOAD&X-Amz-Algorithm=AWS4-HMAC-SHA256&X-Amz-Credential=W7IA3NSYSOQIKLY9DEVC%2F20240617%2Feu-central-1%2Fs3%2Faws4_request&X-Amz-Date=20240617T172839Z&X-Amz-SignedHeaders=host&X-Amz-Expires=518400&X-Amz-Signature=b3bea9d247dce117bc399b640f37ec599e1efab0725dca8c47772476bd815218",
            "author": "羊小凡",
            "pubDate": "Fri, 24 May 2024 17:17:17 +0000",
            "length": "7869275",
            "duration": "197"
        }
    }
}